[
  {
    "id": 1,
    "company": "Vans",
    "shoe": "slip-ons",
    "price": "50 USD",
    "stores": "Off Broadway",
    "phone": "(561) 218-1355",
    "link": "https://www.vans.com/shop/slip-on-navy",
    "img": "https://malala.me/wp-content/uploads/2021/04/Vans.png",
    "class": "vans",
    "class2": "vans2",
    "location": "8210 Glades Rd Boca Raton, FL 33434",
    "coordinates": [-80.175, 26.367],
    "description": "Made with sturdy low profile canvas uppers, the Classic Slip-On is an everyday essential with true “Off The Wall” style. This iconic slip-on shoe also includes supportive padded collars, elastic side accents, and signature rubber waffle outsoles."
  },

  {
    "id": 2,
    "company": "Under Armour",
    "price": "80 USD",
    "shoe": "Charged Covert X Laceless Sneaker",
    "stores": "Under Armour",
    "phone": "(561)693-0000",
    "link": "https://www.lyst.com/shoes/under-armour-charged-covert-x-laceless-sneaker-1/",
    "img": "https://malala.me/wp-content/uploads/2021/04/Under-Armour.png",
    "class": "under",
    "class2": "under2",
    "location": " 1791 Palm Beach Lakes Blvd Suite W115, West Palm Beach, FL 33401",
    "coordinates": [-80.088, 26.726],
    "description": "UA Microthread upper has a comfortable, sock-like fit with embroidered details. Slip-on construction for quick & easy entry. Charged Cushioning provides ultimate comfort. Full rubber outsole for everyday durability."
  },

  {
    "id": 3,
    "company": "Toms",
    "shoe": "Parker Slip On",
    "stores": "DSW",
    "price": "34 USD",
    "phone": "(561) 483-1345",
    "link": "https://www.dsw.com/en/us/product/toms-cupsole-parker-slip-on-sneaker/512643?cm_mmc=CSE-_-GPS-_-G_LIA_Shopping_Loafers%20%26%20Slip%20On-_-LIA_Loafers%20%26%20Slip%20On&cadevice=c&gclid=Cj0KCQjw1a6EBhC0ARIsAOiTkrEK9meu6VQTDJrL9_i-PiQ_R0rxmBNBBqiEcXPFwwWO51IHwYiCOh4aAmdeEALw_wcB&gclsrc=aw.ds",
    "img": "https://malala.me/wp-content/uploads/2021/04/Toms-parker-slip-on.png",
    "class": "toms",
    "class2": "toms2",
    "location": "9870 Glades Road Boca Raton, FL 33434-3917 US",
    "coordinates": [-80.202, 26.365],
    "description": "Seize the day in the Parker, an easy-to-wear slip-on with a durable cupsole and a comfortable insole that keeps feet happier for longer"
  },
  {
    "id": 4,
    "company": "Nike",
    "price": "140 USD",
    "shoe": "React Phantom Run Flyknit 2",
    "stores": "Nike",
    "link": "https://www.nike.com/t/react-phantom-run-flyknit-2-mens-running-shoe-ljcDnm/CJ0277-100?nikemt=true&cp=71606177307_search_%7CPRODUCT_GROUP%7CGOOGLE%7C71700000041489779%7CAll_X_X_X_X-Device_X_Nike-FullPrice_X%7C%7Cc&gclsrc=aw.ds&&gclid=CjwKCAjwj6SEBhAOEiwAvFRuKO-acg0Uy4AGx8ENAYkPIzilZnd2pd_CcKb1R5poicg2W13fVAOOMxoCQ08QAvD_BwE&gclsrc=aw.ds",
    "img": "https://malala.me/wp-content/uploads/2021/04/nike.png",
    "store": "nike",
    "location": "12801 W Sunrise Blvd Ste 1005 Sunrise, FL 33323",
    "class": "phantom",
    "class2": "phantom2",
    "phone": "(954) 837-0329",
    "coordinates": [-80.315, 26.146],
    "description": "The Nike React Phantom Run Flyknit 2 offers versatility for the everyday runner. Building on the foundation of its predecessor, the shoe expands on its laceless design by adding secure support that feels like it `disappears` on your foot. More foam means better cushioning, keeping you comfortable as you run."
  },

  {
    "id": 6,
    "shoe": "Court Legacy Slip",
    "company": "Nike",
    "price": "55 USD",
    "stores": "Nike",
    "link": "https://www.nike.com/t/court-legacy-print-mens-slip-on-SJssls/DA2754-101?nikemt=true&cp=71606177307_search_%7CPRODUCT_GROUP%7CGOOGLE%7C71700000041489779%7CAll_X_X_X_X-Device_X_Nike-FullPrice_X%7C%7Cc&gclsrc=aw.ds&&gclid=Cj0KCQjwsqmEBhDiARIsANV8H3aPp3UTZTY4x6LgA7GjfBpQw3bI_uNhN1xlatf1OiLG0U-X_Bv5fI8aApxLEALw_wcB&gclsrc=aw.ds",
    "img": "https://malala.me/wp-content/uploads/2021/04/Nike-slides.png",
    "location": "12801 W Sunrise Blvd Ste 1005 Sunrise, FL 33323",
    "class": "nike-slip",
    "class2": "nike-slip2",
    "phone": "(954) 837-0329",
    "coordinates": [-80.315, 26.146],
    "description": "Honoring its history rooted in tennis culture, the Nike Court Legacy Slip turns a classic into an easy-to-wear slip-on. Crafted from durable canvas and featuring heritage details like the Swoosh license plate on the back, the style lets you bridge sport and fashion."
  },
  {
    "id": 7,
    "shoe": "Tree Loungers",
    "company": "Allbirds",
    "price": "95 USD",
    "stores": "Walmart",
    "phone": "(561) 226-3157",
    "link": "https://www.allbirds.com/products/mens-tree-loungers-kauri-marine-blue?size=10&iv_=__iv_p_1_g_118109186619_c_499200704540_w_aud-368104966762:pla-1182412973907_n_g_d_c_v__l__t__r__x_pla_y_112866541_f_online_o_TL1MKMR100_z_US_i_en_j_1182412973907_s__e__h_9012018_ii__vi__utm_source=google&utm_medium=shopping&utm_campaign=Shopping+%2F%2F+US+%2F%2F+Allbirds%20Brand+Desktop+Shoes+Slip+Ons&utm_content=499200704540&utm_term=&gclid=Cj0KCQjw1a6EBhC0ARIsAOiTkrESCNKSpWT-QrMv793AcCCuvtiuWzrPIEUs4mzy4Jca3e7CWzFG3O8aArmREALw_wcB",
    "img": "https://malala.me/wp-content/uploads/2021/04/Allbirds.png",
    "class": "allbirds",
    "class2": "allbirds2",
    "location": "22100 FL-7, Boca Raton, FL 33428",
    "coordinates": [-80.201, 26.349],
    "description": "Our breathable slip-on crafted with responsibly sourced eucalyptus tree fiber makes on-the-fly versatility a cinch. Made in Shenzhen, China + Ho Chi Minh, Vietnam"
  },

  {
    "id": 8,
    "shoe": "Slip-Ons",
    "company": "Merino",
    "price": "88 USD",
    "stores": "Walmart",
    "phone": "(561) 226-3157",
    "link": "https://merinoshoes.com/products/dark-grey-womens-slip-ons?variant=32173891977286&currency=USD&utm_medium=product_sync&utm_source=google&utm_content=sag_organic&utm_campaign=sag_organic&gclid=Cj0KCQjw1a6EBhC0ARIsAOiTkrFFJYRPZnCtB21T6oB-sk4mCXZc-5d5J-2k0dQZIOmzPmMJkqa57_oaArZEEALw_wcB",
    "img": "https://malala.me/wp-content/uploads/2021/04/Merinos.png",
    "class": "merino",
    "class2": "merino2",
    "location": "22100 FL-7, Boca Raton, FL 33428",
    "coordinates": [-80.201, 26.349],
    "description": "Soft for daily wear, this reimagined classic made with natural materials is all about balancing simplicity and exaggeration for versatile styling."
  },

  {
    "id": 9,
    "shoe": "Soft Slip-On Sneakers",
    "company": "Ecco",
    "price": "130 USD",
    "stores": "Nordstrom",
    "phone": "(561) 620-5555",
    "link": "https://us.ecco.com/ecco-soft-7-mens-slip-on-sneakers-0825840085303.html?utm_source=google&utm_id=go_cmp-1587138638_adg-58019521577_ad-298404567491_pla-295801472779_dev-c_ext-_prd-0825840085303_sig-Cj0KCQjw1a6EBhC0ARIsAOiTkrEstlm7YHLaHWc2SmWy9p8-EGU1EOj9cWZbB8fJOeUDg6AF6URC2CYaAkhNEALw_wcB&gclid=Cj0KCQjw1a6EBhC0ARIsAOiTkrEstlm7YHLaHWc2SmWy9p8-EGU1EOj9cWZbB8fJOeUDg6AF6URC2CYaAkhNEALw_wcB",
    "img": "https://malala.me/wp-content/uploads/2021/04/Ecco-shoe.png",
    "class": "ecco",
    "class2": "ecco2",
    "location": "5820 GLADES RD, BOCA RATON, FL, 33431",
    "coordinates": [-80.131, 26.364],
    "description": "Embracing ECCO’s core values, the Soft 7 sneaker is a celebration of Scandinavian design with an understated, contemporary twist"
  }
]
